poligon_wrapper/__init__.py
poligon_wrapper/dataloader_alltickers.py
poligon_wrapper/dataloader_stocks.py
poligon_wrapper/logging_config.py
poligon_wrapper/py.typed
poligon_wrapper/utils.py
poligon_wrapper-0.1.1.dist-info/METADATA
poligon_wrapper-0.1.1.dist-info/WHEEL
poligon_wrapper-0.1.1.dist-info/licenses/LICENSE.txt
poligon_wrapper-0.1.1.dist-info/RECORD
