Metadata-Version: 2.4
Name: poligon-wrapper
Version: 0.1.1
Summary: Add your description here
Author-email: fcaretti01 <filippo.caretti@icloud.com>
Maintainer-email: fcaretti01 <filippo.caretti@icloud.com>
License-File: LICENSE.txt
Keywords: api,asyncio,fast,poligon,poligon.io,stocks,wrapper
Requires-Python: >=3.11
Requires-Dist: aiohttp>=3.11.10
Requires-Dist: asyncio>=3.4.3
Requires-Dist: datetime>=5.5
Requires-Dist: logging>=0.4.9.6
Requires-Dist: nest-asyncio>=1.6.0
Requires-Dist: pandas>=2.2.3
Requires-Dist: python-dateutil>=2.9.0.post0
Requires-Dist: python-dotenv>=1.0.1
Requires-Dist: requests>=2.32.3
Requires-Dist: tqdm>=4.67.1
